pagilist/__init__.py
pagilist-0.0.2.dist-info/METADATA
pagilist-0.0.2.dist-info/RECORD
pagilist-0.0.2.dist-info/WHEEL
pagilist-0.0.2.dist-info/top_level.txt
